_punchboot.cpython-312-darwin.so
punchboot/partition.py
punchboot/session.py
punchboot/__init__.py
punchboot/slc.py
punchboot/py.typed
punchboot/helpers.py
punchboot/__main__.py
punchboot/.dylibs/libusb-1.0.0.dylib
punchboot-2.3.0.dist-info/RECORD
punchboot-2.3.0.dist-info/LICENSE
punchboot-2.3.0.dist-info/WHEEL
punchboot-2.3.0.dist-info/entry_points.txt
punchboot-2.3.0.dist-info/top_level.txt
punchboot-2.3.0.dist-info/METADATA
