Metadata-Version: 2.1
Name: punchboot
Version: 2.3.0
Summary: Punchboot tools
Home-page: https://github.com/jonasblixt/punchboot
Author: Jonas Blixt
Author-email: jonpe960@gmail.com
License: BSD
Classifier: Development Status :: 5 - Production/Stable
Classifier: Intended Audience :: Developers
Classifier: Topic :: Software Development :: Embedded Systems
Classifier: License :: OSI Approved :: BSD License
Classifier: Programming Language :: Python :: 3
Classifier: Programming Language :: Python :: 3.8
Classifier: Programming Language :: Python :: 3.9
Classifier: Programming Language :: Python :: 3.10
Classifier: Programming Language :: Python :: 3.11
Classifier: Programming Language :: Python :: 3.12
Requires-Python: >=3.8
License-File: LICENSE
Requires-Dist: semver <4,>=3
Requires-Dist: click <9,>=8
